{
  "cardsData": [
    {
      "url": "https://i.ibb.co/DQbdMGm/image.jpg",
      "name": "Любов Герасимчук",
      "title": "Директор",
      "phone": "+380934139512",
      "description":"Lorem ipsum dolor sit amet, consectetur"
    },
    {
      "url": "https://i.ibb.co/DQbdMGm/image.jpg",
      "name": "Любов Герасимчук",
      "title": "Директор",
      "phone": "+380934139512",
      "description":"Lorem ipsum dolor sit amet, consectetur"
    },
    {
      "url": "https://i.ibb.co/DQbdMGm/image.jpg",
      "name": "Любов Герасимчук",
      "title": "Директор",
      "phone": "+380934139512",
      "description":"Lorem ipsum dolor sit amet, consectetur"
    },
    {
      "url": "https://i.ibb.co/DQbdMGm/image.jpg",
      "name": "Любов Герасимчук",
      "title": "Директор",
      "phone": "+380934139512",
      "description":"Lorem ipsum dolor sit amet, consectetur"
    },
    {
      "url": "https://i.ibb.co/DQbdMGm/image.jpg",
      "name": "Любов Герасимчук",
      "title": "Директор",
      "phone": "+380934139512",
      "description":"Lorem ipsum dolor sit amet, consectetur"
    },
    {
      "url": "https://i.ibb.co/DQbdMGm/image.jpg",
      "name": "Любов Герасимчук",
      "title": "Директор",
      "phone": "+380934139512",
      "description":"Lorem ipsum dolor sit amet, consectetur"
    }
  ]
}
